clipass/__init__.py
clipass/constants.py
clipass/flags.py
clipass/main.py
clipass/passgen.py
clipass/core/__init__.py
clipass/core/base_flags/__init__.py
clipass/core/base_flags/length/__init__.py
clipass/core/base_flags/length/model.py
clipass/core/base_flags/max/__init__.py
clipass/core/base_flags/max/model.py
clipass/core/commands/__init__.py
clipass/core/commands/args.py
clipass/core/models/__init__.py
clipass/core/models/flag_error.py
clipass/core/models/flags.py
clipass/core/models/password_generator.py
clipass/models/__init__.py
clipass-0.0.1.dist-info/LICENSE
clipass-0.0.1.dist-info/METADATA
clipass-0.0.1.dist-info/WHEEL
clipass-0.0.1.dist-info/entry_points.txt
clipass-0.0.1.dist-info/top_level.txt
clipass-0.0.1.dist-info/RECORD
