Metadata-Version: 2.1
Name: clipass
Version: 0.0.1
Summary: CLI passowrd generator
Home-page: https://github.com/itay-bardugo/clipass
Author: Itay Bardugo
Author-email: itaybardugo91@gmail.com
License: UNKNOWN
Platform: UNKNOWN
Classifier: Programming Language :: Python :: 3
Classifier: License :: OSI Approved :: MIT License
Classifier: Operating System :: OS Independent
